<odoo>
	<data noupdate="1">

<!--		SQ-->
		<record id="increment_number_sq_so" model="ir.sequence">
			<field name="name">Increment Number for SQ/SO</field>
			<field name="code">increment.number.sq.so</field>
			<field name="active">TRUE</field>
			<field name="number_next">1</field>
			<field name="number_increment">1</field>
			<field name="padding">4</field>
		</record>

		<record id="increment_number_sq_so_project" model="ir.sequence">
			<field name="name">Increment Number for SQ/SO Project</field>
			<field name="code">increment.number.sq.so.project</field>
			<field name="active">TRUE</field>
			<field name="number_next">1</field>
			<field name="number_increment">1</field>
			<field name="padding">4</field>
		</record>

<!--		Invoice-->
		<record id="increment_number_inv" model="ir.sequence">
			<field name="name">Increment Number for Invoice</field>
			<field name="code">increment.number.inv</field>
			<field name="active">TRUE</field>
			<field name="number_next">1</field>
			<field name="number_increment">1</field>
			<field name="padding">5</field>
		</record>

		<record id="increment_number_inv_pro" model="ir.sequence">
			<field name="name">Increment Number for Invoice Project</field>
			<field name="code">increment.number.inv.pro</field>
			<field name="active">TRUE</field>
			<field name="number_next">1</field>
			<field name="number_increment">1</field>
			<field name="padding">5</field>
		</record>

		<!--		Stock Picking-->
		<record id="increment_number_stock_picking" model="ir.sequence">
			<field name="name">Increment Number for Stock Picking</field>
			<field name="code">increment.number.stock.picking</field>
			<field name="active">TRUE</field>
			<field name="number_next">1</field>
			<field name="number_increment">1</field>
			<field name="padding">4</field>
		</record>

		<!--		Purchase Order-->
		<record id="increment_number_purchase" model="ir.sequence">
			<field name="name">Increment Number for Purchase Order</field>
			<field name="code">increment.number.purchase.order</field>
			<field name="active">TRUE</field>
			<field name="number_next">1</field>
			<field name="number_increment">1</field>
			<field name="padding">5</field>
		</record>

		<!--		Internal Memo-->
		<record id="increment_number_im" model="ir.sequence">
			<field name="name">Increment Number for Internal Memo</field>
			<field name="code">increment.number.internal.memo</field>
			<field name="active">TRUE</field>
			<field name="number_next">1</field>
			<field name="number_increment">1</field>
			<field name="padding">5</field>
		</record>

	</data>
</odoo>